marshmallow_aiohttp/__init__.py
marshmallow_aiohttp/_schemas.py
marshmallow_aiohttp/_trasers.py
marshmallow_aiohttp-0.1.0.dist-info/LICENSE.txt
marshmallow_aiohttp-0.1.0.dist-info/WHEEL
marshmallow_aiohttp-0.1.0.dist-info/METADATA
marshmallow_aiohttp-0.1.0.dist-info/RECORD
